pbpastesrc/__init__.py
pbpastesrc/clipcon.py
pbpaste_win-0.1.1.dist-info/METADATA
pbpaste_win-0.1.1.dist-info/WHEEL
pbpaste_win-0.1.1.dist-info/entry_points.txt
pbpaste_win-0.1.1.dist-info/top_level.txt
pbpaste_win-0.1.1.dist-info/RECORD
