Metadata-Version: 2.1
Name: pbpaste-win
Version: 0.1.1
Summary: A tiny uility to mimic pbpaste in windows.
Home-page: https://github.com/sukhbinder/pbpaste-win
Author: Sukhbinder Singh
Author-email: sukh2010@yahoo.com
Provides-Extra: test
Requires-Dist: pytest ; extra == 'test'
